ripiu/cmsplugin_fup/__init__.py
ripiu/cmsplugin_fup/admin.py
ripiu/cmsplugin_fup/apps.py
ripiu/cmsplugin_fup/cms_plugins.py
ripiu/cmsplugin_fup/models.py
ripiu/cmsplugin_fup/locale/it/LC_MESSAGES/django.po
ripiu/cmsplugin_fup/migrations/0001_initial.py
ripiu/cmsplugin_fup/migrations/0002_auto_20171019_1021.py
ripiu/cmsplugin_fup/migrations/0003_auto_20180409_1325.py
ripiu/cmsplugin_fup/migrations/0004_auto_20180409_1614.py
ripiu/cmsplugin_fup/migrations/__init__.py
ripiu/cmsplugin_fup/migrations/__pycache__/0001_initial.cpython-36.pyc
ripiu/cmsplugin_fup/migrations/__pycache__/0002_auto_20171019_1021.cpython-36.pyc
ripiu/cmsplugin_fup/migrations/__pycache__/0003_auto_20180409_1325.cpython-36.pyc
ripiu/cmsplugin_fup/migrations/__pycache__/0004_auto_20180409_1614.cpython-36.pyc
ripiu/cmsplugin_fup/migrations/__pycache__/__init__.cpython-36.pyc
ripiu/cmsplugin_fup/static/ripiu/cmsplugin_fup/css/fup.css
ripiu/cmsplugin_fup/static/ripiu/cmsplugin_fup/js/fup.js
ripiu/cmsplugin_fup/templates/ripiu/cmsplugin_fup/fup-container.html
ripiu/cmsplugin_fup/templates/ripiu/cmsplugin_fup/fup-item.html
ripiu/cmsplugin_fup/templates/ripiu/cmsplugin_fup/fup.html
ripiu.cmsplugin_fup-0.2.0.dist-info/METADATA
ripiu.cmsplugin_fup-0.2.0.dist-info/RECORD
ripiu.cmsplugin_fup-0.2.0.dist-info/WHEEL
ripiu.cmsplugin_fup-0.2.0.dist-info/top_level.txt
