Metadata-Version: 2.1
Name: ripiu.cmsplugin-fup
Version: 0.2.0
Summary: Fast Undetermined Presentation
Home-page: https://github.com/ripiu/cmsplugin_fup
Author: matteo vezzola
Author-email: matteo@studioripiu.it
License: BSD-new
Platform: UNKNOWN
Classifier: Development Status :: 3 - Alpha
Classifier: Framework :: Django
Classifier: Intended Audience :: Developers
Classifier: License :: OSI Approved :: BSD License
Classifier: Operating System :: OS Independent
Classifier: Programming Language :: Python
Classifier: Topic :: Internet :: WWW/HTTP :: Dynamic Content
Requires-Python: >=3.3
Requires-Dist: Django (>=1.8)
Requires-Dist: django-cms (>=3.1)
Requires-Dist: django-colorfield (<0.2.0,>=0.1.14)
